[
    {
        "trigger": { "url-filter": ".*/reels/.*", "resource-type": ["document"] },
        "action": { "type": "block" }
    },
    {
        "trigger": { "url-filter": ".*/reel/.*", "resource-type": ["document"] },
        "action": { "type": "block" }
    },
    {
        "trigger": { "url-filter": ".*/api/v1/reels/.*" },
        "action": { "type": "block" }
    },
    {
        "trigger": { "url-filter": ".*reels_tray.*" },
        "action": { "type": "block" }
    },
    {
        "trigger": { "url-filter": ".*explore_grid.*" },
        "action": { "type": "block" }
    },
    {
        "trigger": { "url-filter": ".*/api/v1/discover/.*" },
        "action": { "type": "block" }
    },
    {
        "trigger": { "url-filter": ".*/api/v1/ads/.*" },
        "action": { "type": "block" }
    },
    {
        "trigger": { "url-filter": ".*/api/v1/feed/injected_ads/.*" },
        "action": { "type": "block" }
    },
    {
        "trigger": { "url-filter": ".*\\.facebook\\.com/tr/.*" },
        "action": { "type": "block" }
    }
]
